LICENSE.txt
README.md
__init__.py
const.py
data_table.py
generate_ui.bat
sx_item.py
sxtool.py
test_sxtool.py
utils.py
gui/__init__.py
gui/form_insert_row_value.py
gui/form_set_row_size.py
gui/form_split_item.py
gui/insert_dialog.py
gui/main_form.py
gui/paste_dialog.py
gui/ui_form_insert_row_value.py
gui/ui_form_insert_row_value.ui
gui/ui_form_set_row_size.py
gui/ui_form_set_row_size.ui
gui/ui_form_split_item.py
gui/ui_form_split_item.ui
gui/ui_insert_dialog.py
gui/ui_insert_dialog.ui
gui/ui_main_form.py
gui/ui_main_form.ui
gui/ui_paste_dialog.py
gui/ui_paste_dialog.ui
gui/ui_to_py.py
gui/ui_xor_dialog.py
gui/ui_xor_dialog.ui
gui/xor_dialog.py
SxTool-1.1.dist-info/LICENSE.txt
SxTool-1.1.dist-info/METADATA
SxTool-1.1.dist-info/WHEEL
SxTool-1.1.dist-info/entry_points.txt
SxTool-1.1.dist-info/top_level.txt
SxTool-1.1.dist-info/RECORD
