Metadata-Version: 2.1
Name: SxTool
Version: 1.1
Summary: Tool to manipulate SX files (S-records) such as s19 s28 and s37 files
Home-page: https://github.com/bluebird75/sxtool
Author: Philippe Fremy
Author-email: phil.fremy@free.fr
License: BSD
Keywords: sxtool s19 s28 s37
Platform: UNKNOWN
Classifier: Development Status :: 5 - Production/Stable
Classifier: Intended Audience :: Developers
Classifier: License :: OSI Approved :: BSD License
Classifier: Programming Language :: Python :: 3.5
Classifier: Programming Language :: Python :: 3.6
Classifier: Programming Language :: Python :: 3.7
Classifier: Environment :: Win32 (MS Windows)
Classifier: Environment :: X11 Applications :: Qt
Classifier: Operating System :: MacOS :: MacOS X
Classifier: Operating System :: Microsoft :: Windows
Classifier: Topic :: Software Development :: Embedded Systems
Classifier: Topic :: Utilities
Requires-Python: >=3.5
Requires-Dist: pyqt5 (>=5.8)
